CHANGES.txt
README.txt
TO-DO.txt
setup.py
src/plone/__init__.py
src/plone.recipe.unifiedinstaller.egg-info/PKG-INFO
src/plone.recipe.unifiedinstaller.egg-info/SOURCES.txt
src/plone.recipe.unifiedinstaller.egg-info/dependency_links.txt
src/plone.recipe.unifiedinstaller.egg-info/entry_points.txt
src/plone.recipe.unifiedinstaller.egg-info/namespace_packages.txt
src/plone.recipe.unifiedinstaller.egg-info/not-zip-safe
src/plone.recipe.unifiedinstaller.egg-info/requires.txt
src/plone.recipe.unifiedinstaller.egg-info/top_level.txt
src/plone/recipe/__init__.py
src/plone/recipe/unifiedinstaller/__init__.py
src/plone/recipe/unifiedinstaller/admin_text
src/plone/recipe/unifiedinstaller/ctl.py
src/plone/recipe/unifiedinstaller/parts_readme_text
src/plone/recipe/unifiedinstaller/readme_html
src/plone/recipe/unifiedinstaller/readme_text
src/plone/recipe/unifiedinstaller/restart_clients_template
src/plone/recipe/unifiedinstaller/restart_template
src/plone/recipe/unifiedinstaller/shutdown_template
src/plone/recipe/unifiedinstaller/startcluster_template
src/plone/recipe/unifiedinstaller/status_template