Metadata-Version: 1.0
Name: plone.recipe.unifiedinstaller
Version: 4.1
Summary: ZC Buildout recipe for Plone Unified Installer install finalization
Home-page: https://svn.plone.org/svn/collective/buildout/plone.recipe.unifiedinstaller/trunk
Author: Steve McMahon
Author-email: steve@dcn.org
License: ZPL 2.1
Keywords: zope2 buildout
Platform: UNKNOWN
Classifier: License :: OSI Approved :: Zope Public License
Classifier: Framework :: Buildout
Classifier: Framework :: Zope2
Classifier: Programming Language :: Python
